[
  {
    "number": "6285187232856",
    "status": "active"
  },
  {
    "number": "6281322299494",
    "status": "active"
  },
  {
    "number": "6283876025452",
    "status": "active"
  },
  {
    "number": "62895415235000",
    "status": "active"
  },
  {
    "number": "6285860311080",
    "status": "active"
  },
  {
    "number": "6281460495715",
    "status": "active"
  },
  {
    "number": "6288212177705",
    "status": "active"
  },
  {
    "number": "6285721177299",
    "status": "active"
  },
  {
    "number": "6285643533801",
    "status": "active"
  },
  {
    "number": "6285729133075",
    "status": "active"
  },
  {
    "number": "6285607643739",
    "status": "active"
  },
  {
    "number": "6282178117414",
    "status": "active"
  },
  {
    "number": "6285691729985",
    "status": "active"
  },
  {
    "number": "6281297587713",
    "status": "active"
  },
  {
    "number": "6281337425279",
    "status": "active"
  },
  {
    "number": "6282210147088",
    "status": "active"
  },
  {
    "number": "6285174403298",
    "status": "active"
  },
  {
    "number": "6281370552270",
    "status": "active"
  },
  {
    "number": "6281997645161",
    "status": "active"
  },
  {
    "number": "6282348055844",
    "status": "active"
  },
  {
    "number": "6281312538678",
    "status": "active"
  },
  {
    "number": "6283117937912",
    "status": "active"
  },
  {
    "number": "6287820656171",
    "status": "active"
  },
  {
    "number": "6281288199405",
    "status": "active"
  },
  {
    "number": "6281288199406",
    "status": "active"
  },
  {
    "number": "6285783655304",
    "status": "active"
  },
  {
    "number": "62838309136238",
    "status": "active"
  },
  {
    "number": "6283191137623",
    "status": "active"
  },
  {
    "number": "6281398491754",
    "status": "active"
  }
]